pysource/__init__.py
pysource/__main__.py
pysource/conftest.py
pysource/pysource.py
src/__init__.py
src/__main__.py
src/conftest.py
src/pysource.py
pybites_pysource-1.1.0.dist-info/LICENSE
pybites_pysource-1.1.0.dist-info/METADATA
pybites_pysource-1.1.0.dist-info/WHEEL
pybites_pysource-1.1.0.dist-info/entry_points.txt
pybites_pysource-1.1.0.dist-info/top_level.txt
pybites_pysource-1.1.0.dist-info/RECORD
