Metadata-Version: 2.1
Name: pybites-pysource
Version: 1.1.0
Summary: Read Python source code from the command line
Home-page: https://github.com/PyBites-Open-Source/pysource
Author: PyBites
Author-email: support@pybit.es
License: MIT
Platform: UNKNOWN
Classifier: License :: OSI Approved :: MIT License
Classifier: Programming Language :: Python :: 3
Classifier: Programming Language :: Python :: 3.9
